dendrite/__init__.py
dendrite/_cli/__init__.py
dendrite/_cli/main.py
dendrite/_loggers/d_logger.py
dendrite/browser/__init__.py
dendrite/browser/_common/_exceptions/__init__.py
dendrite/browser/_common/_exceptions/_constants.py
dendrite/browser/_common/_exceptions/dendrite_exception.py
dendrite/browser/_common/constants.py
dendrite/browser/_common/types.py
dendrite/browser/async_api/__init__.py
dendrite/browser/async_api/_event_sync.py
dendrite/browser/async_api/_utils.py
dendrite/browser/async_api/browser_impl/__init__.py
dendrite/browser/async_api/browser_impl/browserbase/__init__.py
dendrite/browser/async_api/browser_impl/browserbase/_client.py
dendrite/browser/async_api/browser_impl/browserbase/_download.py
dendrite/browser/async_api/browser_impl/browserbase/_impl.py
dendrite/browser/async_api/browser_impl/browserless/__init__.py
dendrite/browser/async_api/browser_impl/browserless/_impl.py
dendrite/browser/async_api/browser_impl/impl_mapping.py
dendrite/browser/async_api/browser_impl/local/_impl.py
dendrite/browser/async_api/dendrite_browser.py
dendrite/browser/async_api/dendrite_element.py
dendrite/browser/async_api/dendrite_page.py
dendrite/browser/async_api/js/__init__.py
dendrite/browser/async_api/js/eventListenerPatch.js
dendrite/browser/async_api/js/generateDendriteIDs.js
dendrite/browser/async_api/js/generateDendriteIDsIframe.js
dendrite/browser/async_api/manager/__init__.py
dendrite/browser/async_api/manager/navigation_tracker.py
dendrite/browser/async_api/manager/page_manager.py
dendrite/browser/async_api/manager/screenshot_manager.py
dendrite/browser/async_api/mixin/__init__.py
dendrite/browser/async_api/mixin/ask.py
dendrite/browser/async_api/mixin/click.py
dendrite/browser/async_api/mixin/extract.py
dendrite/browser/async_api/mixin/fill_fields.py
dendrite/browser/async_api/mixin/get_element.py
dendrite/browser/async_api/mixin/keyboard.py
dendrite/browser/async_api/mixin/markdown.py
dendrite/browser/async_api/mixin/screenshot.py
dendrite-0.2.8.dist-info/LICENSE
dendrite-0.2.8.dist-info/METADATA
dendrite-0.2.8.dist-info/WHEEL
dendrite-0.2.8.dist-info/entry_points.txt
dendrite-0.2.8.dist-info/RECORD
